biolookup/__init__.py
biolookup/__main__.py
biolookup/api.py
biolookup/cli.py
biolookup/constants.py
biolookup/version.py
biolookup/app/__init__.py
biolookup/app/__main__.py
biolookup/app/backends.py
biolookup/app/blueprints.py
biolookup/app/charts.py
biolookup/app/cli.py
biolookup/app/proxies.py
biolookup/app/wsgi.py
biolookup/app/static/coverage.svg
biolookup/app/static/logo.svg
biolookup/app/templates/base.html
biolookup/app/templates/entity.html
biolookup/app/templates/footer.html
biolookup/app/templates/home.html
biolookup/app/templates/prose.html
biolookup/app/templates/statistics.html
biolookup/app/templates/summary.html
biolookup/app/templates/meta/about.html
biolookup/app/templates/meta/access.html
biolookup/app/templates/meta/download.html
biolookup/backends/__init__.py
biolookup/backends/backend.py
biolookup/backends/memory_backend.py
biolookup/backends/remote_backend.py
biolookup/backends/resolve.py
biolookup/backends/sql_backend.py
biolookup/db/__init__.py
biolookup/db/__main__.py
biolookup/db/cli.py
biolookup/db/loader.py
biolookup-0.2.0.dist-info/LICENSE
biolookup-0.2.0.dist-info/METADATA
biolookup-0.2.0.dist-info/WHEEL
biolookup-0.2.0.dist-info/entry_points.txt
biolookup-0.2.0.dist-info/top_level.txt
biolookup-0.2.0.dist-info/RECORD
