Metadata-Version: 2.1
Name: biolookup
Version: 0.2.0
Summary: Get metadata and ontological information about all biomedical entities.
Home-page: https://github.com/biopragmatics/biolookup
Download-URL: https://github.com/biopragmatics/biolookup/releases
Author: Charles Tapley Hoyt
Author-email: cthoyt@gmail.com
Maintainer: Charles Tapley Hoyt
Maintainer-email: cthoyt@gmail.com
License: MIT
Project-URL: Bug Tracker, https://github.com/biopragmatics/biolookup/issues
Project-URL: Source Code, https://github.com/biopragmatics/biolookup
Keywords: snekpack,cookiecutter
Classifier: Development Status :: 1 - Planning
Classifier: Environment :: Console
Classifier: Intended Audience :: Developers
Classifier: License :: OSI Approved :: MIT License
Classifier: Operating System :: OS Independent
Classifier: Framework :: Pytest
Classifier: Framework :: tox
Classifier: Framework :: Sphinx
Classifier: Programming Language :: Python
Classifier: Programming Language :: Python :: 3.8
Classifier: Programming Language :: Python :: 3.9
Classifier: Programming Language :: Python :: 3.10
Classifier: Programming Language :: Python :: 3 :: Only
Requires-Python: >=3.8
License-File: LICENSE
Requires-Dist: tqdm
Requires-Dist: click
Requires-Dist: more-click
Requires-Dist: pyobo (>=0.6.3)
Requires-Dist: flask
Requires-Dist: bootstrap-flask
Requires-Dist: flasgger
Requires-Dist: psutil
Requires-Dist: sqlalchemy
Requires-Dist: psycopg2-binary
Requires-Dist: tabulate
Provides-Extra: docs
Requires-Dist: sphinx ; extra == 'docs'
Requires-Dist: sphinx-rtd-theme ; extra == 'docs'
Requires-Dist: sphinx-click ; extra == 'docs'
Requires-Dist: sphinx-autodoc-typehints ; extra == 'docs'
Requires-Dist: sphinx-automodapi ; extra == 'docs'
Provides-Extra: tests
Requires-Dist: pytest ; extra == 'tests'
Requires-Dist: coverage ; extra == 'tests'
